ddrp/__init__.py
ddrp/config.py
ddrp/plot_utils.py
ddr_p-0.2.1.dist-info/WHEEL
ddr_p-0.2.1.dist-info/METADATA
ddr_p-0.2.1.dist-info/RECORD
